powerline_treesitter/__init__.py
powerline_treesitter/segments.py
powerline_treesitter-0.2.0.dist-info/LICENSE
powerline_treesitter-0.2.0.dist-info/METADATA
powerline_treesitter-0.2.0.dist-info/WHEEL
powerline_treesitter-0.2.0.dist-info/top_level.txt
powerline_treesitter-0.2.0.dist-info/RECORD
